profiles/Coef_Manager.py
profiles/Meta.py
profiles/Profile.py
profiles/Profile_Set.py
profiles/Raw_Profile.py
profiles/Thermo_Profile.py
profiles/UnitFormatter.py
profiles/Wind_Profile.py
profiles/__init__.py
profiles/conf.py
profiles/mavlogdump_Profiles.py
profiles/plotting.py
profiles/utils.py
oucass_profiles-1.3.0.dist-info/LICENSE
oucass_profiles-1.3.0.dist-info/METADATA
oucass_profiles-1.3.0.dist-info/WHEEL
oucass_profiles-1.3.0.dist-info/top_level.txt
oucass_profiles-1.3.0.dist-info/RECORD
